libsrg/AppTemplate.py
libsrg/Config.py
libsrg/ElapsedTime.py
libsrg/Info.py
libsrg/LevelBanner.py
libsrg/LoggingAppBase.py
libsrg/LoggingCounter.py
libsrg/LoggingUtils.py
libsrg/LoggingWatcher.py
libsrg/NagiosBase.py
libsrg/Runner.py
libsrg/Runner2.py
libsrg/__init__.py
libsrg/Statistics/ADStatsBase.py
libsrg/Statistics/AnalogStatsBase.py
libsrg/Statistics/AnalogStatsCumulative.py
libsrg/Statistics/AnalogStatsFading.py
libsrg/Statistics/AnalogStatsSlidingWindow.py
libsrg/Statistics/DiscreteStatsBase.py
libsrg/Statistics/DiscreteStatsCumulative.py
libsrg/Statistics/DiscreteStatsSlidingWindow.py
libsrg/Statistics/__init__.py
libsrg-6.1.0.dist-info/METADATA
libsrg-6.1.0.dist-info/WHEEL
libsrg-6.1.0.dist-info/top_level.txt
libsrg-6.1.0.dist-info/RECORD
