Metadata-Version: 2.4
Name: libsrg
Version: 6.1.0
Summary: Utility lib logging, statistics, subprocesses
Author-email: Steve Goncalo <steven@goncalo.us>
License: MIT
Classifier: Programming Language :: Python :: 3.10
Classifier: Development Status :: 5 - Production/Stable
Classifier: License :: OSI Approved :: MIT License
Classifier: Operating System :: POSIX :: Linux
Classifier: Natural Language :: English
Classifier: Topic :: Utilities
Classifier: Intended Audience :: Developers
Requires-Python: >=3.10
Requires-Dist: jinja2>=3.1.5
Requires-Dist: numpy>=2.2.2
